mehditor/__init__.py
mehditor/app_commands.py
mehditor/config.py
mehditor/main.py
mehditor/screens/__init__.py
mehditor/screens/about.py
mehditor/screens/app_menu.py
mehditor/screens/chooser.py
mehditor/screens/confirm_dialog.py
mehditor/screens/file_chooser.py
mehditor/screens/file_open.py
mehditor/screens/file_save.py
mehditor/screens/file_settings.py
mehditor/screens/hotkeys.py
mehditor/screens/input_prompt.py
mehditor/screens/mehditor_app.py
mehditor/screens/quit_screen.py
mehditor/screens/shortcuts.py
mehditor/validators.py
mehditor/widgets/__init__.py
mehditor/widgets/better_text_area.py
mehditor-0.2.0.dist-info/METADATA
mehditor-0.2.0.dist-info/WHEEL
mehditor-0.2.0.dist-info/entry_points.txt
mehditor-0.2.0.dist-info/RECORD
